cbadenes_sales/sales.py
cbadenes_sales/settings.py
cbadenes_sales-0.0.1.dist-info/METADATA
cbadenes_sales-0.0.1.dist-info/WHEEL
cbadenes_sales-0.0.1.dist-info/licenses/LICENSE
cbadenes_sales-0.0.1.dist-info/RECORD
