Metadata-Version: 2.1
Name: cbadenes_sales
Version: 0.0.1
Summary: My customized ORM on Sales
Project-URL: Homepage, https://github.com/bigdatainf/sales
Project-URL: Bug Tracker, https://github.com/bigdatainf/sales/issues
Author-email: cbadenes <carlos.badenes@upm.es>
License: MIT License
License-File: LICENSE
Classifier: License :: OSI Approved :: MIT License
Classifier: Operating System :: OS Independent
Classifier: Programming Language :: Python :: 3
Requires-Python: >=3.9
